rubin/citsci/__init__.py
rubin/citsci/pipeline.py
rubin_citsci-0.8.1.dist-info/licenses/LICENSE
rubin_citsci-0.8.1.dist-info/METADATA
rubin_citsci-0.8.1.dist-info/WHEEL
rubin_citsci-0.8.1.dist-info/top_level.txt
rubin_citsci-0.8.1.dist-info/RECORD
