Metadata-Version: 2.4
Name: rubin.citsci
Version: 0.8.1
Summary: The companion package to the Rubin citizen science notebooks.
Author: Eric Rosas
Author-email: eric.rosas@noirlab.edu
Project-URL: Homepage, https://rubinobservatory.org/for-scientists/citizen-science
License-File: LICENSE
Requires-Dist: panoptes_client
Requires-Dist: google.cloud.storage
Requires-Dist: requests
Dynamic: license-file
